{
  "notices": [
    {
      "title": "Admission Open 2026–27",
      "date": "2026-02-05",
      "year": 2026,
      "link": "notices/admission.pdf",
      "latest": true,
      "new": true
    },
    {
      "title": "Parent Teacher Meeting",
      "date": "2026-02-15",
      "year": 2026,
      "link": "notices/ptm.pdf",
      "latest": true,
      "new": true
    },
    {
      "title": "Annual Sports Day",
      "date": "2025-12-20",
      "year": 2025,
      "link": "notices/sports.pdf"
    }
  ]
}
